{
  "description": "Explore 24 hours open restaurants in Hyderabad. Find late-night eateries, cafes, and street food spots serving delicious meals any time",
  "raw_path": "raw\\firecrawl_search\\safe_late_night_cafes_in_Hyderabad-0-bcc90fe08ac7.json",
  "search_query": "safe late night cafes in Hyderabad",
  "search_rank": 3,
  "source": "firecrawl_search",
  "source_type": "search_result",
  "title": "24 Hours Open Restaurants in Hyderabad | Late Night Eats 2025",
  "url": "https://fooddy.in/blog/24-hours-open-restaurants-in-hyderabad/"
}